[
  {
    "id": 1,
    "name": "frutas",
    "description": "frutas frescas",
    "products": [
      {
        "id": 1,
        "name": "Potatoes",
        "cost": 0.4,
        "pvp": 0.6,
        "description": "1 lb of potatoes",
        "provider": "Vegetables Inc."
      }
    ]
  },
  {
    "id": 2,
    "name": "verduras",
    "description": "verduras frescas",
    "products": []
  },
  {
    "id": 3,
    "name": "carnes",
    "description": "frutas frescas",
    "products": []
  },
  {
    "id": 4,
    "name": "snacks",
    "description": "snacks pepsico",
    "products": []
  },
  {
    "id": 0,
    "name": "verduras",
    "description": "verduras",
    "products": [
      {
        "id": 1,
        "name": "Potatoes",
        "cost": 0.4,
        "pvp": 0.6,
        "description": "1 lb of potatoes",
        "provider": "Vegetables Inc."
      }
    ]
  }
]